cfuzzyset.cp311-win_amd64.pyd
fuzzyset/__init__.py
fuzzyset2-0.2.4.dist-info/METADATA
fuzzyset2-0.2.4.dist-info/WHEEL
fuzzyset2-0.2.4.dist-info/top_level.txt
fuzzyset2-0.2.4.dist-info/RECORD
