Metadata-Version: 2.1
Name: fuzzyset2
Version: 0.2.4
Summary: A simple python fuzzyset implementation.
Home-page: https://github.com/alpae/fuzzyset/
Author: Michael Axiak, Adrian Altenhoff
Author-email: adrian.altenhoff@inf.ethz.ch
License: BSD
Keywords: fuzzyset fuzzy data structure
Classifier: Development Status :: 5 - Production/Stable
Classifier: License :: OSI Approved :: BSD License
Classifier: Operating System :: OS Independent
Classifier: Programming Language :: Python
Classifier: Topic :: Software Development :: Libraries
Requires-Python: >=3.6
Requires-Dist: rapidfuzz >=2.0
